harakiri/__init__.py
harakiri/client.py
harakiri/model.py
Harakiri-0.2.3.dist-info/LICENSE
Harakiri-0.2.3.dist-info/METADATA
Harakiri-0.2.3.dist-info/WHEEL
Harakiri-0.2.3.dist-info/top_level.txt
Harakiri-0.2.3.dist-info/RECORD
