Metadata-Version: 2.1
Name: Harakiri
Version: 0.2.3
Summary: ManjiApi Wrapper
Home-page: https://github.com/ManjiKR/Harakiri
Author: ombe1229
Author-email: h3236516@gmail.com
License: Apache-2.0
Platform: UNKNOWN
